ReText/__init__.py
ReText/__main__.py
ReText/config.py
ReText/converterprocess.py
ReText/dialogs.py
ReText/editor.py
ReText/fakevimeditor.py
ReText/filesystemmodel.py
ReText/highlighter.py
ReText/icontheme.py
ReText/mdx_posmap.py
ReText/preview.py
ReText/syncscroll.py
ReText/tab.py
ReText/tabledialog.py
ReText/tablemode.py
ReText/webenginepreview.py
ReText/window.py
ReText/xsettings.py
ReText/icons/application-exit.png
ReText/icons/application-pdf.png
ReText/icons/document-new.png
ReText/icons/document-open-folder.png
ReText/icons/document-open-recent.png
ReText/icons/document-open.png
ReText/icons/document-preview.png
ReText/icons/document-print-preview.png
ReText/icons/document-print.png
ReText/icons/document-save-as.png
ReText/icons/document-save.png
ReText/icons/edit-copy.png
ReText/icons/edit-cut.png
ReText/icons/edit-find.png
ReText/icons/edit-paste.png
ReText/icons/edit-redo.png
ReText/icons/edit-undo.png
ReText/icons/go-next.png
ReText/icons/go-previous.png
ReText/icons/help-about.png
ReText/icons/internet-web-browser.png
ReText/icons/retext.png
ReText/icons/retext.svg
ReText/icons/system-file-manager.png
ReText/icons/text-html.png
ReText/icons/view-fullscreen.png
ReText/icons/x-office-document.png
ReText/locale/retext_ar.qm
ReText/locale/retext_ca.qm
ReText/locale/retext_cs.qm
ReText/locale/retext_cy.qm
ReText/locale/retext_da.qm
ReText/locale/retext_de.qm
ReText/locale/retext_es.qm
ReText/locale/retext_es_CO.qm
ReText/locale/retext_et.qm
ReText/locale/retext_eu.qm
ReText/locale/retext_fa.qm
ReText/locale/retext_fi.qm
ReText/locale/retext_fr.qm
ReText/locale/retext_ga.qm
ReText/locale/retext_hr.qm
ReText/locale/retext_hu.qm
ReText/locale/retext_it.qm
ReText/locale/retext_ja.qm
ReText/locale/retext_ko.qm
ReText/locale/retext_nl.qm
ReText/locale/retext_no.qm
ReText/locale/retext_pl.qm
ReText/locale/retext_pt.qm
ReText/locale/retext_pt_BR.qm
ReText/locale/retext_ru.qm
ReText/locale/retext_sk.qm
ReText/locale/retext_sr.qm
ReText/locale/retext_sr@latin.qm
ReText-8.1.0.dist-info/LICENSE_GPL
ReText-8.1.0.dist-info/METADATA
ReText-8.1.0.dist-info/WHEEL
ReText-8.1.0.dist-info/entry_points.txt
ReText-8.1.0.dist-info/top_level.txt
ReText-8.1.0.dist-info/RECORD
