Metadata-Version: 2.2
Name: ReText
Version: 8.1.0
Summary: Simple editor for Markdown and reStructuredText
Author-email: Dmitry Shachnev <mitya57@gmail.com>
License: GPL-2.0-or-later
Project-URL: Homepage, https://github.com/retext-project/retext
Project-URL: Wiki, https://github.com/retext-project/retext/wiki
Project-URL: Issue Tracker, https://github.com/retext-project/retext/issues
Classifier: Development Status :: 5 - Production/Stable
Classifier: Environment :: X11 Applications :: Qt
Classifier: License :: OSI Approved :: GNU General Public License v2 or later (GPLv2+)
Classifier: Programming Language :: Python :: 3 :: Only
Classifier: Topic :: Text Editors
Classifier: Topic :: Text Processing :: Markup
Requires-Python: >=3.9
License-File: LICENSE_GPL
Requires-Dist: Markups[markdown,restructuredtext]>=4.0
Requires-Dist: Pygments
Requires-Dist: PyQt6
Provides-Extra: spellcheck
Requires-Dist: pyenchant; extra == "spellcheck"
Provides-Extra: encoding-detection
Requires-Dist: chardet; extra == "encoding-detection"
Provides-Extra: webengine
Requires-Dist: PyQt6-WebEngine; extra == "webengine"
